fastapi_bootstrapper/__init__.py
fastapi_bootstrapper/cli.py
fastapi_bootstrapper-0.1.1.dist-info/licenses/LICENSE
fastapi_bootstrapper-0.1.1.dist-info/METADATA
fastapi_bootstrapper-0.1.1.dist-info/WHEEL
fastapi_bootstrapper-0.1.1.dist-info/entry_points.txt
fastapi_bootstrapper-0.1.1.dist-info/top_level.txt
fastapi_bootstrapper-0.1.1.dist-info/RECORD
