Metadata-Version: 2.4
Name: fastapi-bootstrapper
Version: 0.1.1
Summary: A CLI tool to scaffold FastAPI and LLM-ready Python project structures.
Author-email: Chaithanya K <cchaithanya83@gmail.com>
Requires-Python: >=3.8
License-File: LICENSE
Requires-Dist: python-dotenv
Requires-Dist: concurrent-log-handler
Dynamic: license-file
